[
	{ "fileName": "anishinaabe-berry.png", "name": "berry", "category": "Quilting" },
	{ "fileName": "anishinaabe-bigpetal.png", "name": "big petal", "category": "Quilting" },
	{ "fileName": "anishinaabe-bud1.png", "name": "bud 1", "category": "Quilting" },
	{ "fileName": "anishinaabe-flower1.png", "name": "flower 1", "category": "Quilting" },
	{ "fileName": "anishinaabe-flower2.png", "name": "flower 2", "category": "Quilting" },
	{ "fileName": "anishinaabe-leaf1.png", "name": "leaf 1", "category": "Quilting" },
	{ "fileName": "anishinaabe-medicinewheel.png", "name": "medicine wheel", "category": "Quilting" },
	{ "fileName": "anishinaabe-petal.png", "name": "petal", "category": "Quilting" },
	{ "fileName": "anishinaabe-petal2.png", "name": "petal 2", "category": "Quilting" },
	{ "fileName": "appalachian-blond.png", "name": "appalachian blond", "category": "Quilting" },
	{ "fileName": "appalachian-green.png", "name": "appalachian green", "category": "Quilting" },
	{ "fileName": "appalachian-plaid.png", "name": "appalachian plaid", "category": "Quilting" },
	{ "fileName": "appalachian-rose.png", "name": "appalachian rose", "category": "Quilting" },
	{ "fileName": "appalachian-white.png", "name": "appalachian white", "category": "Quilting" },
	{ "fileName": "fourdirections-head.png", "name": "head", "category": "Quilting" },
	{ "fileName": "fourdirections-human.png", "name": "human", "category": "Quilting" },
	{ "fileName": "fourdirections-kite.png", "name": "kite", "category": "Quilting" },
	{ "fileName": "fourdirections-rhombus1.png", "name": "rhombus1", "category": "Quilting" },
	{ "fileName": "fourdirections-rhombus2.png", "name": "rhombus2", "category": "Quilting" },
	{ "fileName": "fourdirections-triangle1.png", "name": "triangle1", "category": "Quilting" },
	{ "fileName": "fourdirections-triangle2.png", "name": "triangle2", "category": "Quilting" },
	{ "fileName": "fourdirections-turtle_island.png", "name": "turtle_island", "category": "Quilting" },
	{ "fileName": "fourdirections-turtlefoot.png", "name": "turtlefoot", "category": "Quilting" },
	{ "fileName": "fourdirections-turtlehead.png", "name": "turtlehead", "category": "Quilting" },
	{ "fileName": "gees-gb_unit1.png", "name": "unit 1", "category": "Quilting" },
	{ "fileName": "gees-gb_unit2.png", "name": "unit 2", "category": "Quilting" },
	{ "fileName": "gees-stripe.png", "name": "stripe", "category": "Quilting" },
	{ "fileName": "gees-stripes.png", "name": "stripes", "category": "Quilting" },
	{ "fileName": "gees-stripes3.png", "name": "stripes3", "category": "Quilting" },
	{ "fileName": "lakota-rhombus.png", "name": "rhombus", "category": "Quilting" },
	{ "fileName": "lakota-rhombus1.png", "name": "rhombus1", "category": "Quilting" },
	{ "fileName": "socialjustice-breakTheseChains.png", "name": "breakTheseChains", "category": "Social Justice" },
	{ "fileName": "socialjustice-dontShoot.png", "name": "dontShoot", "category": "Social Justice" },
	{ "fileName": "socialjustice-dove.png", "name": "dove", "category": "Social Justice" },
	{ "fileName": "socialjustice-dreads2.png", "name": "dreads2", "category": "Social Justice" },
	{ "fileName": "socialjustice-fist.png", "name": "fist", "category": "Social Justice" },
	{ "fileName": "socialjustice-heart.png", "name": "heart", "category": "Social Justice" },
	{ "fileName": "socialjustice-hipHop.png", "name": "hipHop", "category": "Social Justice" },
	{ "fileName": "socialjustice-libertyBell.png", "name": "libertyBell", "category": "Social Justice" },
	{ "fileName": "socialjustice-micHand.png", "name": "micHand", "category": "Social Justice" },
	{ "fileName": "socialjustice-peace2.png", "name": "peace2", "category": "Social Justice" },
	{ "fileName": "socialjustice-quincunx.png", "name": "quincunx", "category": "Social Justice" },
	{ "fileName": "socialjustice-scaleOfJustice.png", "name": "scaleOfJustice", "category": "Social Justice" },
	{ "fileName": "socialjustice-write.png", "name": "write", "category": "Social Justice" },
	{ "fileName": "sports-motion0.png", "name": "motion0", "category": "Sports" },
	{ "fileName": "sports-motion1.png", "name": "motion1", "category": "Sports" },
	{ "fileName": "sports-motion2.png", "name": "motion2", "category": "Sports" },
	{ "fileName": "sports-motion3.png", "name": "motion3", "category": "Sports" },
	{ "fileName": "sports-motion4.png", "name": "motion4", "category": "Sports" },
	{ "fileName": "adinkra-funtunfunefu.png", "name": "funtunfunefu", "category": "Adinkra" },
	{ "fileName": "adinkra-gyenayme.png", "name": "gyenayme", "category": "Adinkra" },
	{ "fileName": "adinkra-mmeredane.png", "name": "mmeredane", "category": "Adinkra" },
	{ "fileName": "adinkra-mpatapo.png", "name": "mpatapo", "category": "Adinkra" },
	{ "fileName": "adinkra-mpuannum.png", "name": "mpuannum", "category": "Adinkra" },
	{ "fileName": "adinkra-odonnyewfiekwan.png", "name": "odonnyewfiekwan", "category": "Adinkra" },
	{ "fileName": "adinkra-sankofa.png", "name": "sankofa", "category": "Adinkra" },
	{ "fileName": "adinkra-sepow.png", "name": "sepow", "category": "Adinkra" },
	{ "fileName": "adinkra-adinkrahene.png", "name": "adinkrahene", "category": "Adinkra" },
	{ "fileName": "adinkra-akokonan.png", "name": "akokonan", "category": "Adinkra" },
	{ "fileName": "adinkra-akoma.png", "name": "akoma", "category": "Adinkra" },
	{ "fileName": "adinkra-ananse.png", "name": "ananse", "category": "Adinkra" },
	{ "fileName": "adinkra-asaseyeduru.png", "name": "asaseyeduru", "category": "Adinkra" },
	{ "fileName": "adinkra-aya.png", "name": "aya", "category": "Adinkra" },
	{ "fileName": "adinkra-dwennimmen.png", "name": "dwennimmen", "category": "Adinkra" },
	{ "fileName": "adinkra-epa.png", "name": "epa", "category": "Adinkra" },
	{ "fileName": "eban.png", "name": "eban", "category": "Adinkra" },
	{ "fileName": "akofena.png", "name": "akofena", "category": "Adinkra" },
	{ "fileName": "akon.png", "name": "akoma ntoso", "category": "Adinkra" },
	{ "fileName": "bese.png", "name": "bese saka", "category": "Adinkra" },
	{ "fileName": "bink.png", "name": "bi nka bi", "category": "Adinkra" },
	{ "fileName": "boam.png", "name": "boa me na me mmoa wo", "category": "Adinkra" },
	{ "fileName": "denk.png", "name": "denkyem", "category": "Adinkra" },
	{ "fileName": "duafe.png", "name": "duafe", "category": "Adinkra" },
	{ "fileName": "esen.png", "name": "ese ne tekrema", "category": "Adinkra" },
	{ "fileName": "fawo.png", "name": "fawohodie", "category": "Adinkra" },
	{ "fileName": "fiha.png", "name": "fihankra", "category": "Adinkra" },
	{ "fileName": "fofo.png", "name": "fofo", "category": "Adinkra" },
	{ "fileName": "hwem.png", "name": "hwemudua", "category": "Adinkra" },
	{ "fileName": "hyew.png", "name": "hye wonhye", "category": "Adinkra" },
	{ "fileName": "ketepa.png", "name": "kete pa", "category": "Adinkra" },
	{ "fileName": "kint.png", "name": "kintinkantan", "category": "Adinkra" },
	{ "fileName": "kwat.png", "name": "kwatakye atiko", "category": "Adinkra" },
	{ "fileName": "mate.png", "name": "nate masie", "category": "Adinkra" },
	{ "fileName": "mewarewo.png", "name": "me ware wo", "category": "Adinkra" },
	{ "fileName": "mfra.png", "name": "mframadan", "category": "Adinkra" },
	{ "fileName": "mmus.png", "name": "mmusuyidee", "category": "Adinkra" },
	{ "fileName": "neao.png", "name": "nea onnim no sua a, ohu", "category": "Adinkra" },
	{ "fileName": "neaope.png", "name": "nea ope se obedi hene", "category": "Adinkra" },
	{ "fileName": "nkon.png", "name": "nkonsonkonson", "category": "Adinkra" },
	{ "fileName": "nyamedua.png", "name": "nyame dua", "category": "Adinkra" },
	{ "fileName": "nkyi.png", "name": "nkyinkyim", "category": "Adinkra" },
	{ "fileName": "nsaa.png", "name": "nsaa", "category": "Adinkra" },
	{ "fileName": "nsor.png", "name": "nsoromma", "category": "Adinkra" },
	{ "fileName": "nyabi.png", "name": "nyame biribi wo soro", "category": "Adinkra" },
	{ "fileName": "nyawu.png", "name": "nyame nnwu na mawu", "category": "Adinkra" },
	{ "fileName": "nyame-nti.png", "name": "nyame nti", "category": "Adinkra" },
	{ "fileName": "nyameohene.png", "name": "nyame ye ohene", "category": "Adinkra" },
	{ "fileName": "nyan.png", "name": "nyansapo", "category": "Adinkra" },
	{ "fileName": "okodee.png", "name": "okodee mmowere", "category": "Adinkra" },
	{ "fileName": "onyan.png", "name": "onyankopon adom nti biribiara beye yie", "category": "Adinkra" },
	{ "fileName": "osra.png", "name": "osram ne nssoromma", "category": "Adinkra" },
	{ "fileName": "owof.png", "name": "owo foro adobe", "category": "Adinkra" },
	{ "fileName": "owuo-atwedee.png", "name": "owuo atwedee", "category": "Adinkra" },
	{ "fileName": "pemp.png", "name": "pempansie", "category": "Adinkra" },
	{ "fileName": "sesa.png", "name": "sesa wo suban", "category": "Adinkra" },
	{ "fileName": "tamf.png", "name": "tamfo bebre", "category": "Adinkra" },
	{ "fileName": "wawa.png", "name": "wawa aba", "category": "Adinkra" },
	{ "fileName": "wofo.png", "name": "woforo dua pa a", "category": "Adinkra" },
	{ "fileName": "wonsa.png", "name": "wo nsa da mu a", "category": "Adinkra" },
	{ "fileName": "nkyimu.png", "name": "nkyimu", "category": "Adinkra" },
	{ "fileName": "dame.png", "name": "dame-dame", "category": "Adinkra" },
	{ "fileName": "moneybag1.png", "name": "money bag", "category": "Social Justice" },
	{ "fileName": "tear.png", "name": "teardrop", "category": "Social Justice" },
	{ "fileName": "forbiddensign.png", "name": "forbidden sign", "category": "Social Justice" },
	{ "fileName": "equality.png", "name": "equality", "category": "Social Justice" },
	{ "fileName": "dove.png", "name": "dove2", "category": "Social Justice" },
	{ "fileName": "crown.png", "name": "crown", "category": "Social Justice" },
	{ "fileName": "hands.png", "name": "hands", "category": "Social Justice" },
	{ "fileName": "tupac.png", "name": "Tupac", "category": "Musicians" },
	{ "fileName": "martinluther.png", "name": "MLK", "category": "Inspirational People" },
	{ "fileName": "harriett-tubman.png", "name": "Harriet Tubman", "category": "Inspirational People" },
	{ "fileName": "mlk.png", "name": "MLK2", "category": "Inspirational People" },
	{ "fileName": "barack_obama.png", "name": "Barack Obama", "category": "Inspirational People" },
	{ "fileName": "george_floyd.png", "name": "George Floyd", "category": "Inspirational People" },
	{ "fileName": "malcolmx.png", "name": "Malcolm X", "category": "Inspirational People" },
	{ "fileName": "angeladavis.png", "name": "Angela Davis", "category": "Inspirational People" },
	{ "fileName": "blackpanther.png", "name": "Black Panther", "category": "Inspirational People" },
	{ "fileName": "chadwick-boseman.png", "name": "Chadwick Boseman", "category": "Inspirational People" },
	{ "fileName": "mae_jemison.png", "name": "Mae Jemison", "category": "Inspirational People" },
	{ "fileName": "neil-degrasse-tyson.png", "name": "Neil Degrasse Tyson", "category": "Inspirational People" },
	{ "fileName": "suri.png", "name": "Shuri", "category": "Inspirational People" },
	{ "fileName": "juicewrld.gif", "name": "Juice Wrld", "category": "Musicians" },
	{ "fileName": "soccer1.png", "name": "Soccer1", "category": "Sports" },
	{ "fileName": "soccer2.png", "name": "Soccer2", "category": "Sports" },
	{ "fileName": "soccer3.png", "name": "Soccer3", "category": "Sports" },
	{ "fileName": "soccer4.png", "name": "Soccer4", "category": "Sports" },
	{ "fileName": "dance1.png", "name": "Dance1", "category": "Sports" },
	{ "fileName": "dance2.png", "name": "Dance2", "category": "Sports" },
	{ "fileName": "dance3.png", "name": "Dance3", "category": "Sports" },
	{ "fileName": "dance4.png", "name": "Dance4", "category": "Sports" },
	{ "fileName": "bulldog.png", "name": "Bulldog", "category": "Animals" },
	{ "fileName": "alicia-garza.png", "name": "Alicia Garza", "category": "Inspirational People" },
	{ "fileName": "black-arts-matter.png", "name": "Black Arts Matter", "category": "Social Justice" },
	{ "fileName": "peace-sign.png", "name": "Peace Sign", "category": "Social Justice" },
	{ "fileName": "political-solidarity.png", "name": "Political Solidarity Activism", "category": "Social Justice" },
	{ "fileName": "cat.png", "name": "Cat", "category": "Animals" },
	{ "fileName": "headphones.png", "name": "Headphones", "category": "Misc" },
	{ "fileName": "headphones-2.png", "name": "Headphones 2", "category": "Misc" },
	{ "fileName": "hyena.png", "name": "Hyena", "category": "Animals" },
	{ "fileName": "lion.png", "name": "Lion", "category": "Animals" },
	{ "fileName": "mustang.png", "name": "Mustang", "category": "Animals" },
	{ "fileName": "mustang-2.png", "name": "Mustang 2", "category": "Animals" },
	{ "fileName": "panther-1.png", "name": "Panther", "category": "Animals" },
	{ "fileName": "panther-2.png", "name": "Panther 2", "category": "Animals" },
	{ "fileName": "panther-3.png", "name": "Panther 3", "category": "Animals" },
	{ "fileName": "tiger.png", "name": "Tiger", "category": "Animals" },
	{ "fileName": "kamala-harris.png", "name": "Kamala Harris", "category": "Inspirational People" },
	{ "fileName": "unity-hands.png", "name": "Unity", "category": "Social Justice" },
	{ "fileName": "the-weeknd.png", "name": "The Weeknd", "category": "Musicians" },
	{ "fileName": "the-weeknd-2.png", "name": "The Weeknd 2", "category": "Musicians" },
	{ "fileName": "SZA.png", "name": "SZA", "category": "Musicians" },
	{ "fileName": "SZA-2.png", "name": "SZA 2", "category": "Musicians" },
	{ "fileName": "rihanna.png", "name": "Rihanna", "category": "Musicians" },
	{ "fileName": "pharrel.png", "name": "Pharrel", "category": "Musicians" },
	{ "fileName": "pharrel-2.png", "name": "Pharrel 2", "category": "Musicians" },
	{ "fileName": "notoriousBIG.png", "name": "Notorious B.I.G.", "category": "Musicians" },
	{ "fileName": "nicki-minaj.png", "name": "Nicki Minaj", "category": "Musicians" },
	{ "fileName": "nicki-minaj-2.png", "name": "Nicki Minaj 2", "category": "Musicians" },
	{ "fileName": "mlk-3.png", "name": "Martin Luther King Jr.", "category": "Inspirational People" },
	{ "fileName": "lilWayne-2.png", "name": "Lil Wayne 2", "category": "Musicians" },
	{ "fileName": "lil-wayne.png", "name": "Lil Wayne", "category": "Musicians" },
	{ "fileName": "kendrick-lamar.png", "name": "Kendrick Lamar", "category": "Musicians" },
	{ "fileName": "kendrick-lamar-2.png", "name": "Kendrick Lamar 2", "category": "Musicians" },
	{ "fileName": "kanye-west.png", "name": "Kayne West", "category": "Musicians" },
	{ "fileName": "jayZ.png", "name": "Jay-Z", "category": "Musicians" },
	{ "fileName": "hands-2.png", "name": "Holding Hands", "category": "Social Justice" },
	{ "fileName": "face.png", "name": "Face", "category": "Musicians" },
	{ "fileName": "easyE.png", "name": "Easy E", "category": "Musicians" },
	{ "fileName": "drake.png", "name": "Drake", "category": "Musicians" },
	{ "fileName": "cardiB.png", "name": "Cardi B", "category": "Musicians" },
	{ "fileName": "cardiB-2.png", "name": "Cardi B 2", "category": "Musicians" },
	{ "fileName": "beyonce.png", "name": "Beyonce", "category": "Musicians" },
	{ "fileName": "beyonce-2.png", "name": "Beyonce", "category": "Musicians" },
	{ "fileName": "american_flag.png", "name": "American Flag", "category": "AST Base" },
	{ "fileName": "american_gothic.jpg", "name": "American Gothic", "category": "AST Base" },
	{ "fileName": "caduceus.png", "name": "Caduceus", "category": "AST Base" },
	{ "fileName": "campbell_soup.jpg", "name": "Campbells Soup", "category": "AST Base" },
	{ "fileName": "dove_base.png", "name": "Dove", "category": "AST Base" },
	{ "fileName": "einstein.jpg", "name": "Albert Einstein", "category": "AST Base" },
	{ "fileName": "frederick_douglass.jpg", "name": "Frederick Douglass", "category": "AST Base" },
	{ "fileName": "george_washington.jpg", "name": "George Washington", "category": "AST Base" },
	{ "fileName": "handshake_of_solidarity.jpg", "name": "Handshake of Solidarity", "category": "AST Base" },
	{ "fileName": "jemison.jpg", "name": "Mae Jemison", "category": "AST Base" },
	{ "fileName": "m_toni_morrison.jpeg", "name": "Toni Morrison", "category": "AST Base" },
	{ "fileName": "millenium_falcon.jpg", "name": "Millenium Falcon", "category": "AST Base" },
	{ "fileName": "mona_lisa.jpg", "name": "Mona Lisa", "category": "AST Base" },
	{ "fileName": "obama.jpg", "name": "Barack Obama", "category": "AST Base" },
	{ "fileName": "pdiddy.jpg", "name": "P Diddy", "category": "AST Base" },
	{ "fileName": "pug.jpg", "name": "Pug", "category": "AST Base" },
	{ "fileName": "rhianna.jpg", "name": "Rhianna", "category": "AST Base" },
	{ "fileName": "sacagawea.jpg", "name": "Sacagawea", "category": "AST Base" },
	{ "fileName": "statue_of_liberty.jpg", "name": "Statue of Liberty", "category": "AST Base" },
	{ "fileName": "the_thinker.jpg", "name": "The Thinker", "category": "AST Base" },
	{ "fileName": "two_hands.jpeg", "name": "Two Hands", "category": "AST Base" },
	{ "fileName": "art-1.png", "name": "Yayoi Kusama", "category": "AST Base" },
	{ "fileName": "art-2.png", "name": "Salvador Dalí", "category": "AST Base" },
	{ "fileName": "art-3.png", "name": "Van Gogh", "category": "AST Base" },
	{ "fileName": "art-4.png", "name": "Jean-Michel Basquiat", "category": "AST Base" },
	{ "fileName": "art-5.png", "name": "Andy Warhol", "category": "AST Base" },
	{ "fileName": "adinkra_cloth.png", "name": "Adinkra Cloth", "category": "AST Style" },
	{ "fileName": "adire_cloth.png", "name": "Adire Cloth", "category": "AST Style" },
	{ "fileName": "gara.png", "name": "Gara Cloth", "category": "AST Style" },
	{ "fileName": "kente_cloth.png", "name": "Kente Cloth", "category": "AST Style" },
	{ "fileName": "kuba_cloth.png", "name": "Kuba Cloth", "category": "AST Style" },
	{ "fileName": "mud_cloth.png", "name": "Mud Cloth", "category": "AST Style" },
	{ "fileName": "ndebelle_mural.png", "name": "Ndebelle Mural", "category": "AST Style" },
	{ "fileName": "zulu_basket.png", "name": "Zulu Basket", "category": "AST Style" },
	{ "fileName": "barong-bangkal-rs.png", "name": "Barong Bangkal", "category": "Bali" },
	{ "fileName": "barong-gajah-rs.png", "name": "Barong Gajah", "category": "Bali" },
	{ "fileName": "barong-gajah.png", "name": "Barong Gajah", "category": "Bali" },
	{ "fileName": "barong-ket-ear.png", "name": "Barong Ket Ear", "category": "Bali" },
	{ "fileName": "barong-ket-fur.png", "name": "Barong Ket Fur", "category": "Bali" },
	{ "fileName": "barong-ket-mouth.png", "name": "Barong Ket Mouth", "category": "Bali" },
	{ "fileName": "barong-ket-nose.png", "name": "Barong Ket Nose", "category": "Bali" },
	{ "fileName": "barong-ket-rs.png", "name": "Barong Ket", "category": "Bali" },
	{ "fileName": "barong-macan-rs.png", "name": "Barong Macan", "category": "Bali" },
	{ "fileName": "eyes-jaran-guyang.png", "name": "Eyes Jaran Guyang", "category": "Bali" },
	{ "fileName": "fangs-jaran-guyang.png", "name": "Fangs Jaran Guyang", "category": "Bali" },
	{ "fileName": "flame.png", "name": "Flame", "category": "Bali" },
	{ "fileName": "hanuman-crown.png", "name": "Hanuman Crown", "category": "Bali" },
	{ "fileName": "hanuman-ear.png", "name": "Hanuman Ear", "category": "Bali" },
	{ "fileName": "hanuman-filigree.png", "name": "Hanuman Filigree", "category": "Bali" },
	{ "fileName": "hanuman-fur.png", "name": "Hanuman Fur", "category": "Bali" },
	{ "fileName": "hanuman-mouth.png", "name": "Hanuman Mouth", "category": "Bali" },
	{ "fileName": "hanuman-round-filigree.png", "name": "Hanuman Round Filigree", "category": "Bali" },
	{ "fileName": "hanuman-rs.png", "name": "Hanuman", "category": "Bali" },
	{ "fileName": "jaran-guyang-tongue.png", "name": "Jaran Guyang Tongue", "category": "Bali" },
	{ "fileName": "jayatu-rs.png", "name": "Jayatu", "category": "Bali" },
	{ "fileName": "make-a-scene-dragon-rs.png", "name": "Make a Scene Dragon", "category": "Bali" },
	{ "fileName": "nose-jaran-guyang.png", "name": "Nose Jaran Guyang", "category": "Bali" },
	{ "fileName": "pak-kaler-surata-rs.png", "name": "Pak Kaler Surata", "category": "Bali" },
	{ "fileName": "pak-ron-eglash-rs.png", "name": "Pak Ron Eglash", "category": "Bali" }
]
